{"article_id": 100461, "submitted": "2021-02-22 08:06:52", "suggest": ["dobbeltspent"], "lemmas": [{"final_lexeme": "spent", "hgno": 0, "id": 158747, "inflection_class": "a2", "initial_lexeme": "dobbelt", "lemma": "dobbeltspent", "paradigm_info": [{"from": "2014-01-01", "inflection": [{"tags": ["Pos", "Masc/Fem", "Ind", "Sing"], "word_form": "dobbeltspent"}, {"tags": ["Pos", "Plur"], "word_form": "dobbeltspente"}, {"tags": ["Pos", "Def", "Sing"], "word_form": "dobbeltspente"}, {"tags": ["Pos", "Neuter", "Ind", "Sing"], "word_form": "dobbeltspent"}, {"tags": [], "word_form": null}, {"tags": [], "word_form": null}, {"tags": [], "word_form": null}], "inflection_group": "ADJ_regular", "paradigm_id": 452, "standardisation": "STANDARD", "tags": ["ADJ"], "to": null}], "split_inf": false}], "body": {"pronunciation": [], "definitions": [{"type_": "definition", "elements": [{"type_": "explanation", "content": "$", "items": [{"type_": "article_ref", "article_id": 10477, "lemmas": [{"type_": "lemma", "hgno": 0, "id": 12248, "lemma": "dobbeltknappet"}, {"type_": "lemma", "hgno": 0, "id": 12247, "lemma": "dobbeltknappa"}], "definition_id": null}]}, {"type_": "example", "quote": {"content": "en $ jakke", "items": [{"type_": "usage", "text": "dobbeltspent"}]}, "explanation": {"content": "", "items": []}}], "id": 2}]}, "to_index": ["dobbeltspent"], "author": "14", "edit_state": "Eksisterende", "referers": [], "status": 8, "updated": "2022-02-23 23:30:14"}