{"article_id": 102611, "submitted": "2021-04-16 08:15:28", "suggest": ["harde konsonanter"], "lemmas": [{"final_lexeme": "harde konsonanter", "hgno": 0, "id": 1144773, "lemma": "harde konsonanter", "mo_link": 0, "paradigm_info": [{"from": "2019-01-01", "inflection": [{"tags": [], "word_form": "harde konsonanter"}], "inflection_group": "EXPR", "paradigm_id": 2470, "standardisation": "REGISTERED", "tags": ["EXPR"], "to": null}], "split_inf": false, "stress_vowel": 0}], "body": {"pronunciation": [], "definitions": [{"type_": "definition", "elements": [{"type_": "explanation", "content": "$ konsonanter", "items": [{"type_": "article_ref", "article_id": 65001, "lemmas": [{"type_": "lemma", "hgno": 0, "id": 74439, "lemma": "ustemt"}], "definition_id": 4, "definition_order": 2, "word_form": "ustemte"}]}, {"type_": "explanation", "content": "til forskjell fra $", "items": [{"type_": "article_ref", "article_id": 101068, "lemmas": [{"type_": "lemma", "hgno": 0, "id": 1146122, "lemma": "bløte konsonanter"}], "definition_id": null}]}, {"type_": "example", "quote": {"content": "p, t og k er harde konsonanter", "items": []}, "explanation": {"content": "", "items": []}}, {"type_": "explanation", "content": "Se: $", "items": [{"type_": "article_ref", "article_id": 22387, "lemmas": [{"lemma": "hard"}]}]}], "id": 2}]}, "author": "USD_LEKS_BOKMAALSORDBOKA", "edit_state": "Eksisterende", "referers": [{"article_id": 101068, "hgno": 0, "lemma": "bløte konsonanter"}, {"article_id": 22387, "hgno": 0, "lemma": "hard"}], "status": 8, "updated": "2022-07-27 09:03:10"}