{"article_id": 103741, "submitted": "2022-01-21 11:48:34", "suggest": ["på loffen"], "lemmas": [{"final_lexeme": "på loffen", "hgno": 0, "id": 1144922, "lemma": "på loffen", "mo_link": 0, "paradigm_info": [{"from": "2019-01-01", "inflection": [{"tags": [], "word_form": "på loffen"}], "inflection_group": "EXPR", "paradigm_id": 2470, "standardisation": "REGISTERED", "tags": ["EXPR"], "to": null}], "split_inf": false, "stress_vowel": 0}], "body": {"pronunciation": [], "definitions": [{"type_": "definition", "elements": [{"type_": "explanation", "content": "på vandring eller reise uten fast arbeid og tilholdssted", "items": []}, {"type_": "example", "quote": {"content": "fattigfolk som gikk på loffen i 1930-årene", "items": []}, "explanation": {"content": "", "items": []}}, {"type_": "example", "quote": {"content": "de tok et år på loffen i Asia", "items": []}, "explanation": {"content": "", "items": []}}, {"type_": "explanation", "content": "Se: $", "items": [{"type_": "article_ref", "article_id": 35634, "lemmas": [{"lemma": "loff"}]}]}], "id": 2}]}, "author": "USD_LEKS_BOKMAALSORDBOKA", "edit_state": "Eksisterende", "referers": [{"article_id": 35634, "hgno": 2, "lemma": "loff"}, {"article_id": 35635, "hgno": 1, "lemma": "loffe"}, {"article_id": 121876, "hgno": 0, "lemma": "loffer"}], "status": 8, "updated": "2023-05-16 12:27:25"}