{"article_id": 116742, "submitted": "2021-08-23 15:53:09", "suggest": ["hekling"], "lemmas": [{"final_lexeme": "hekling", "hgno": 0, "id": 105653, "inflection_class": "m1, f1", "lemma": "hekling", "paradigm_info": [{"from": "1996-01-01", "inflection": [{"tags": ["Sing", "Ind"], "word_form": "hekling"}, {"tags": ["Sing", "Def"], "word_form": "heklingen"}, {"tags": ["Plur", "Ind"], "word_form": "heklinger"}, {"tags": ["Plur", "Def"], "word_form": "heklingene"}], "inflection_group": "NOUN_regular", "paradigm_id": 564, "standardisation": "STANDARD", "tags": ["NOUN", "Masc"], "to": null}, {"from": "1996-01-01", "inflection": [{"tags": ["Sing", "Ind"], "word_form": "hekling"}, {"tags": ["Sing", "Def"], "word_form": "heklinga"}, {"tags": ["Plur", "Ind"], "word_form": "heklinger"}, {"tags": ["Plur", "Def"], "word_form": "heklingene"}], "inflection_group": "NOUN_regular", "paradigm_id": 760, "standardisation": "STANDARD", "tags": ["NOUN", "Fem"], "to": null}], "split_inf": false}], "body": {"pronunciation": [], "definitions": [{"type_": "definition", "elements": [{"type_": "definition", "elements": [{"type_": "explanation", "content": "det 책 $", "items": [{"type_": "article_ref", "article_id": 22915, "lemmas": [{"type_": "lemma", "hgno": 3, "id": 26989, "lemma": "hekle"}], "definition_id": null}]}, {"type_": "example", "quote": {"content": "drive med strikking og hekling p책 fritiden", "items": []}, "explanation": {"content": "", "items": []}}], "id": 3}, {"type_": "definition", "elements": [{"type_": "explanation", "content": "noe en holder p책 med 책 hekle eller har heklet", "items": []}], "id": 4}], "id": 2}]}, "author": "17", "edit_state": "Utjamning", "referers": [], "status": 8, "updated": "2023-10-10 12:25:44"}