{"article_id": 126722, "submitted": "2023-02-28 09:14:54", "suggest": ["rusmiddelbruk"], "lemmas": [{"annotated_lemma": null, "final_lexeme": "bruk", "hgno": 0, "id": 2096014, "inflection_class": "m1,n.", "initial_lexeme": "rusmiddel", "lemma": "rusmiddelbruk", "markdown_lemma": "rusmiddelbruk", "paradigm_info": [{"from": "1996-01-01", "inflection": [{"markdown_word_form": "rusmiddelbruk", "tags": ["Sing", "Ind"], "word_form": "rusmiddelbruk"}, {"markdown_word_form": "rusmiddelbruken", "tags": ["Sing", "Def"], "word_form": "rusmiddelbruken"}, {"markdown_word_form": "rusmiddelbruker", "tags": ["Plur", "Ind"], "word_form": "rusmiddelbruker"}, {"markdown_word_form": "rusmiddelbrukene", "tags": ["Plur", "Def"], "word_form": "rusmiddelbrukene"}], "inflection_group": "NOUN_regular", "paradigm_id": 564, "standardisation": "STANDARD", "tags": ["NOUN", "Masc"], "to": null}, {"from": "1996-01-01", "inflection": [{"markdown_word_form": "rusmiddelbruk", "tags": ["Sing", "Ind"], "word_form": "rusmiddelbruk"}, {"markdown_word_form": "rusmiddelbruket", "tags": ["Sing", "Def"], "word_form": "rusmiddelbruket"}, {"markdown_word_form": "rusmiddelbruk", "tags": ["Plur", "Ind"], "word_form": "rusmiddelbruk"}, {"markdown_word_form": "rusmiddelbruka", "tags": ["Plur", "Def"], "word_form": "rusmiddelbruka"}], "inflection_group": "NOUN_regular", "paradigm_id": 669, "standardisation": "STANDARD", "tags": ["NOUN", "Neuter"], "to": null}, {"from": "1996-01-01", "inflection": [{"markdown_word_form": "rusmiddelbruk", "tags": ["Sing", "Ind"], "word_form": "rusmiddelbruk"}, {"markdown_word_form": "rusmiddelbruket", "tags": ["Sing", "Def"], "word_form": "rusmiddelbruket"}, {"markdown_word_form": "rusmiddelbruk", "tags": ["Plur", "Ind"], "word_form": "rusmiddelbruk"}, {"markdown_word_form": "rusmiddelbrukene", "tags": ["Plur", "Def"], "word_form": "rusmiddelbrukene"}], "inflection_group": "NOUN_regular", "paradigm_id": 679, "standardisation": "STANDARD", "tags": ["NOUN", "Neuter"], "to": null}], "split_inf": false}], "body": {"definitions": [{"type_": "definition", "elements": [{"type_": "explanation", "content": "det å bruke rusmidler", "items": []}], "id": 1, "sub_definition": false}]}, "author": "15", "edit_state": "Ny", "referers": [], "status": 8, "updated": "2024-07-01 10:42:15"}