{"article_id": 132965, "submitted": "2024-04-29 05:48:25", "suggest": ["trygdemottaker", "trygdemottager"], "lemmas": [{"added_norm": false, "final_lexeme": "mottaker", "hgno": 0, "id": 148621, "inflection_class": "m2", "initial_lexeme": "trygd", "junction": "e", "lemma": "trygdemottaker", "paradigm_info": [{"from": "1996-01-01", "inflection": [{"tags": ["Sing", "Ind"], "word_form": "trygdemottaker"}, {"tags": ["Sing", "Def"], "word_form": "trygdemottakeren"}, {"tags": ["Plur", "Ind"], "word_form": "trygdemottakere"}, {"tags": ["Plur", "Def"], "word_form": "trygdemottakerne"}], "inflection_group": "NOUN_regular", "paradigm_id": 576, "standardisation": "STANDARD", "tags": ["NOUN", "Masc"], "to": null}], "split_inf": false}, {"added_norm": false, "final_lexeme": "mottager", "hgno": 0, "id": 2853891, "inflection_class": "m2", "initial_lexeme": "trygde", "lemma": "trygdemottager", "paradigm_info": [{"from": "1996-01-01", "inflection": [{"tags": ["Sing", "Ind"], "word_form": "trygdemottager"}, {"tags": ["Sing", "Def"], "word_form": "trygdemottageren"}, {"tags": ["Plur", "Ind"], "word_form": "trygdemottagere"}, {"tags": ["Plur", "Def"], "word_form": "trygdemottagerne"}], "inflection_group": "NOUN_regular", "paradigm_id": 576, "standardisation": "STANDARD", "tags": ["NOUN", "Masc"], "to": null}], "split_inf": false}], "body": {"definitions": [{"type_": "definition", "elements": [{"type_": "explanation", "content": "mottaker av $", "items": [{"type_": "article_ref", "article_id": 62572, "lemmas": [{"type_": "lemma", "hgno": 0, "id": 71603, "lemma": "trygd"}], "definition_id": 4, "definition_order": 2}]}], "id": 1, "sub_definition": false}]}, "author": "14", "edit_state": "Ny", "referers": [], "status": 8, "updated": "2024-12-18 08:10:29"}