{"article_id": 15736, "submitted": "2021-09-01 10:53:18", "suggest": ["fnugglett"], "lemmas": [{"final_lexeme": "lett", "hgno": 0, "id": 18280, "inflection_class": "a2", "initial_lexeme": "fnugg", "lemma": "fnugglett", "paradigm_info": [{"from": "2014-01-01", "inflection": [{"tags": ["Pos", "Masc/Fem", "Ind", "Sing"], "word_form": "fnugglett"}, {"tags": ["Pos", "Plur"], "word_form": "fnugglette"}, {"tags": ["Pos", "Def", "Sing"], "word_form": "fnugglette"}, {"tags": ["Pos", "Neuter", "Ind", "Sing"], "word_form": "fnugglett"}, {"tags": [], "word_form": null}, {"tags": [], "word_form": null}, {"tags": [], "word_form": null}], "inflection_group": "ADJ_regular", "paradigm_id": 452, "standardisation": "STANDARD", "tags": ["ADJ"], "to": null}], "split_inf": false}], "body": {"pronunciation": [], "definitions": [{"type_": "definition", "elements": [{"type_": "explanation", "content": "lett som et $", "items": [{"type_": "article_ref", "article_id": 15735, "lemmas": [{"type_": "lemma", "hgno": 0, "id": 18279, "lemma": "fnugg"}], "definition_id": 2, "definition_order": 1}]}], "id": 2}]}, "author": "14", "edit_state": "Eksisterende", "referers": [], "status": 8, "updated": "2022-02-23 23:30:14"}