{"article_id": 34153, "submitted": "2016-12-05 01:51:19", "suggest": ["layoute"], "lemmas": [{"final_lexeme": "layoute", "hgno": 0, "id": 40137, "lemma": "layoute", "paradigm_info": [{"from": "1996-01-01", "inflection": [{"tags": ["Inf"], "word_form": "layoute"}, {"tags": [], "word_form": null}, {"tags": ["Pres"], "word_form": "layouter"}, {"tags": ["Inf", "Pass"], "word_form": "layoutes"}, {"tags": ["Pres", "Pass"], "word_form": "layoutes"}, {"tags": ["Past"], "word_form": "layouta"}, {"tags": ["<PerfPart>"], "word_form": "layouta"}, {"tags": ["Adj", "<PerfPart>", "Neuter", "Ind", "Sing"], "word_form": "layouta"}, {"tags": ["Adj", "<PerfPart>", "Masc/Fem", "Ind", "Sing"], "word_form": "layouta"}, {"tags": [], "word_form": null}, {"tags": ["Adj", "<PerfPart>", "Def", "Sing"], "word_form": "layouta"}, {"tags": ["Adj", "<PerfPart>", "Plur"], "word_form": "layouta"}, {"tags": ["Adj", "<PresPart>"], "word_form": "layoutende"}, {"tags": ["Imp"], "word_form": "layout"}, {"tags": [], "word_form": null}, {"tags": [], "word_form": null}], "inflection_group": "VERB_regular", "paradigm_id": 1, "standardisation": "STANDARD", "tags": ["VERB"], "to": null}, {"from": "1996-01-01", "inflection": [{"tags": ["Inf"], "word_form": "layoute"}, {"tags": [], "word_form": null}, {"tags": ["Pres"], "word_form": "layouter"}, {"tags": ["Inf", "Pass"], "word_form": "layoutes"}, {"tags": ["Pres", "Pass"], "word_form": "layoutes"}, {"tags": ["Past"], "word_form": "layoutet"}, {"tags": ["<PerfPart>"], "word_form": "layoutet"}, {"tags": ["Adj", "<PerfPart>", "Neuter", "Ind", "Sing"], "word_form": "layoutet"}, {"tags": ["Adj", "<PerfPart>", "Masc/Fem", "Ind", "Sing"], "word_form": "layoutet"}, {"tags": [], "word_form": null}, {"tags": ["Adj", "<PerfPart>", "Def", "Sing"], "word_form": "layoutete"}, {"tags": ["Adj", "<PerfPart>", "Plur"], "word_form": "layoutete"}, {"tags": ["Adj", "<PresPart>"], "word_form": "layoutende"}, {"tags": ["Imp"], "word_form": "layout"}, {"tags": [], "word_form": null}, {"tags": [], "word_form": null}], "inflection_group": "VERB_regular", "paradigm_id": 6, "standardisation": "STANDARD", "tags": ["VERB"], "to": null}, {"from": "1996-01-01", "inflection": [{"tags": ["Inf"], "word_form": "layoute"}, {"tags": [], "word_form": null}, {"tags": ["Pres"], "word_form": "layouter"}, {"tags": ["Inf", "Pass"], "word_form": "layoutes"}, {"tags": ["Pres", "Pass"], "word_form": "layoutes"}, {"tags": ["Past"], "word_form": "layoutet"}, {"tags": ["<PerfPart>"], "word_form": "layoutet"}, {"tags": ["Adj", "<PerfPart>", "Neuter", "Ind", "Sing"], "word_form": "layoutet"}, {"tags": ["Adj", "<PerfPart>", "Masc/Fem", "Ind", "Sing"], "word_form": "layoutet"}, {"tags": [], "word_form": null}, {"tags": ["Adj", "<PerfPart>", "Def", "Sing"], "word_form": "layoutede"}, {"tags": ["Adj", "<PerfPart>", "Plur"], "word_form": "layoutede"}, {"tags": ["Adj", "<PresPart>"], "word_form": "layoutende"}, {"tags": ["Imp"], "word_form": "layout"}, {"tags": [], "word_form": null}, {"tags": [], "word_form": null}], "inflection_group": "VERB_regular", "paradigm_id": 7, "standardisation": "STANDARD", "tags": ["VERB"], "to": null}]}], "body": {"pronunciation": [{"type_": "pronunciation", "content": "utt leiaute", "items": []}], "definitions": [{"type_": "definition", "elements": [{"type_": "explanation", "content": "arbeide med, utføre layout", "items": []}], "id": 2}]}}