{"article_id": 37311, "submitted": "2022-02-13 18:03:59", "suggest": ["masseødeleggelsesvåpen"], "lemmas": [{"final_lexeme": "våpen", "hgno": 0, "id": 43738, "inflection_class": "n.", "initial_lexeme": "masseødeleggelse", "junction": "s", "lemma": "masseødeleggelsesvåpen", "paradigm_info": [{"from": "1996-01-01", "inflection": [{"tags": ["Sing", "Ind"], "word_form": "masseødeleggelsesvåpen"}, {"tags": ["Sing", "Def"], "word_form": "masseødeleggelsesvåpenet"}, {"tags": ["Plur", "Ind"], "word_form": "masseødeleggelsesvåpen"}, {"tags": ["Plur", "Def"], "word_form": "masseødeleggelsesvåpna"}], "inflection_group": "NOUN_regular", "paradigm_id": 684, "standardisation": "STANDARD", "tags": ["NOUN", "Neuter"], "to": null}, {"from": "1996-01-01", "inflection": [{"tags": ["Sing", "Ind"], "word_form": "masseødeleggelsesvåpen"}, {"tags": ["Sing", "Def"], "word_form": "masseødeleggelsesvåpenet"}, {"tags": ["Plur", "Ind"], "word_form": "masseødeleggelsesvåpen"}, {"tags": ["Plur", "Def"], "word_form": "masseødeleggelsesvåpnene"}], "inflection_group": "NOUN_regular", "paradigm_id": 685, "standardisation": "STANDARD", "tags": ["NOUN", "Neuter"], "to": null}], "split_inf": false}], "body": {"definitions": [{"type_": "definition", "elements": [{"type_": "explanation", "content": "våpen med evne til $ og til å ta svært mange liv", "items": [{"type_": "article_ref", "article_id": 37309, "lemmas": [{"type_": "lemma", "hgno": 0, "id": 43736, "lemma": "masseødeleggelse"}], "definition_id": null}]}, {"type_": "example", "quote": {"content": "atomvåpen, biologiske våpen og kjemiske våpen blir regnet som masseødeleggelsesvåpen", "items": []}, "explanation": {"content": "", "items": []}}], "id": 1, "sub_definition": false}]}, "author": "17", "edit_state": "Eksisterende", "referers": [], "status": 8, "updated": "2023-12-07 17:12:54"}