{"article_id": 42925, "submitted": "2024-11-18 11:23:22", "suggest": ["øvre"], "lemmas": [{"added_norm": false, "final_lexeme": "øvre", "hgno": 0, "id": 81239, "lemma": "øvre", "paradigm_info": [{"from": "1996-01-01", "inflection": [{"tags": [], "word_form": null}, {"tags": [], "word_form": null}, {"tags": [], "word_form": null}, {"tags": [], "word_form": null}, {"tags": ["Cmp"], "word_form": "øvre"}, {"tags": ["Sup", "Ind"], "word_form": "øverst"}, {"tags": ["Sup", "Def"], "word_form": "øverste"}], "inflection_group": "ADJ_regular", "paradigm_id": 522, "standardisation": "STANDARD", "tags": ["ADJ"], "to": null}], "split_inf": false}], "body": {"etymology": [{"type_": "etymology_reference", "content": "$ $", "items": [{"type_": "entity", "id": "norr."}, {"type_": "usage", "text": "øfri"}]}, {"type_": "etymology_reference", "content": "$ $", "items": [{"type_": "entity", "id": "jf"}, {"type_": "article_ref", "article_id": 42917, "lemmas": [{"type_": "lemma", "hgno": 0, "id": 81225, "lemma": "øverst"}]}]}], "definitions": [{"type_": "definition", "elements": [{"type_": "definition", "elements": [{"type_": "explanation", "content": "som er eller ligger lenger oppe", "items": [], "attest": []}, {"type_": "explanation", "content": "$ $", "items": [{"type_": "entity", "id": "mots"}, {"type_": "article_ref", "article_id": 40522, "lemmas": [{"type_": "lemma", "hgno": 0, "id": 47431, "lemma": "nedre"}]}], "attest": []}, {"type_": "example", "quote": {"content": "den $ delen av eiendommen", "items": [{"type_": "usage", "text": "øvre"}]}, "explanation": {"content": "", "items": []}, "attest": []}], "id": 3, "sub_definition": false}, {"type_": "definition", "elements": [{"type_": "explanation", "content": "lengst oppe", "items": [], "attest": []}, {"type_": "explanation", "content": "øverst", "items": [], "attest": []}, {"type_": "example", "quote": {"content": "den $ av de to hyttene", "items": [{"type_": "usage", "text": "øvre"}]}, "explanation": {"content": "", "items": []}, "attest": []}], "id": 4, "sub_definition": false}, {"type_": "definition", "elements": [{"type_": "explanation", "content": "som er i det høyeste området på en skala", "items": [], "attest": []}, {"type_": "example", "quote": {"content": "i øvre prisklasse", "items": []}, "explanation": {"content": "", "items": []}, "attest": []}, {"type_": "example", "quote": {"content": "sette en $ grense for antall deltakere", "items": [{"type_": "usage", "text": "øvre"}]}, "explanation": {"content": "", "items": []}, "attest": []}], "id": 1, "sub_definition": false}], "id": 2, "sub_definition": false}]}, "to_index": ["øfri", "øvre", "øvre", "øvre"], "author": "15", "edit_state": "Eksisterende", "referers": [{"article_id": 7198, "hgno": 0, "lemma": "boven-"}, {"article_id": 40522, "hgno": 0, "lemma": "nedre"}, {"article_id": 42917, "hgno": 0, "lemma": "øverst"}], "status": 8, "updated": "2024-12-18 12:01:18"}