{"article_id": 50873, "submitted": "2024-05-30 11:02:03", "suggest": ["senestrekk"], "lemmas": [{"final_lexeme": "strekk", "hgno": 0, "id": 58551, "inflection_class": "m1, n.", "initial_lexeme": "sene", "lemma": "senestrekk", "mo_link": 0, "paradigm_info": [{"from": "1996-01-01", "inflection": [{"tags": ["Sing", "Ind"], "word_form": "senestrekk"}, {"tags": ["Sing", "Def"], "word_form": "senestrekken"}, {"tags": ["Plur", "Ind"], "word_form": "senestrekker"}, {"tags": ["Plur", "Def"], "word_form": "senestrekkene"}], "inflection_group": "NOUN_regular", "paradigm_id": 564, "standardisation": "STANDARD", "tags": ["NOUN", "Masc"], "to": null}, {"from": "1996-01-01", "inflection": [{"tags": ["Sing", "Ind"], "word_form": "senestrekk"}, {"tags": ["Sing", "Def"], "word_form": "senestrekket"}, {"tags": ["Plur", "Ind"], "word_form": "senestrekk"}, {"tags": ["Plur", "Def"], "word_form": "senestrekka"}], "inflection_group": "NOUN_regular", "paradigm_id": 669, "standardisation": "STANDARD", "tags": ["NOUN", "Neuter"], "to": null}, {"from": "1996-01-01", "inflection": [{"tags": ["Sing", "Ind"], "word_form": "senestrekk"}, {"tags": ["Sing", "Def"], "word_form": "senestrekket"}, {"tags": ["Plur", "Ind"], "word_form": "senestrekk"}, {"tags": ["Plur", "Def"], "word_form": "senestrekkene"}], "inflection_group": "NOUN_regular", "paradigm_id": 679, "standardisation": "STANDARD", "tags": ["NOUN", "Neuter"], "to": null}], "split_inf": false, "stress_vowel": 0}], "body": {"definitions": [{"type_": "definition", "elements": [{"type_": "definition", "elements": [{"type_": "explanation", "content": "skade som kommer av at en har forstrekt en $", "items": [{"type_": "article_ref", "article_id": 50865, "lemmas": [{"type_": "lemma", "hgno": 1, "id": 58543, "lemma": "sene"}, {"type_": "lemma", "hgno": 1, "id": 81854, "lemma": "sen"}], "definition_id": 2, "definition_order": 1}], "attest": []}, {"type_": "explanation", "content": "$", "items": [{"type_": "article_ref", "article_id": 57604, "lemmas": [{"type_": "lemma", "hgno": 1, "id": 65958, "lemma": "strekk"}], "definition_id": 3, "definition_order": 3}], "attest": []}], "id": 2, "sub_definition": false}, {"type_": "definition", "elements": [{"type_": "explanation", "content": "smertefull, krampaktig sammentrekning av muskulaturen", "items": [], "attest": []}], "id": 4, "sub_definition": false}], "id": 3, "sub_definition": false}]}, "author": "Bente Selback", "edit_state": "Eksisterende", "referers": [{"article_id": 50875, "hgno": 0, "lemma": "senetrekning"}], "status": 8, "updated": "2025-02-05 15:10:33"}