{"article_id": 51465, "submitted": "2023-11-10 10:17:12", "suggest": ["sikte"], "lemmas": [{"final_lexeme": "sikte", "hgno": 3, "id": 59175, "inflection_class": "v1", "lemma": "sikte", "paradigm_info": [{"from": "1996-01-01", "inflection": [{"tags": ["Inf"], "word_form": "sikte"}, {"tags": [], "word_form": null}, {"tags": ["Pres"], "word_form": "sikter"}, {"tags": ["Inf", "Pass"], "word_form": "siktes"}, {"tags": ["Pres", "Pass"], "word_form": "siktes"}, {"tags": ["Past"], "word_form": "sikta"}, {"tags": ["<PerfPart>"], "word_form": "sikta"}, {"tags": ["Adj", "<PerfPart>", "Neuter", "Ind", "Sing"], "word_form": "sikta"}, {"tags": ["Adj", "<PerfPart>", "Masc/Fem", "Ind", "Sing"], "word_form": "sikta"}, {"tags": [], "word_form": null}, {"tags": ["Adj", "<PerfPart>", "Def", "Sing"], "word_form": "sikta"}, {"tags": ["Adj", "<PerfPart>", "Plur"], "word_form": "sikta"}, {"tags": ["Adj", "<PresPart>"], "word_form": "siktende"}, {"tags": ["Imp"], "word_form": "sikt"}, {"tags": [], "word_form": null}, {"tags": [], "word_form": null}], "inflection_group": "VERB_regular", "paradigm_id": 1, "standardisation": "STANDARD", "tags": ["VERB"], "to": null}, {"from": "1996-01-01", "inflection": [{"tags": ["Inf"], "word_form": "sikte"}, {"tags": [], "word_form": null}, {"tags": ["Pres"], "word_form": "sikter"}, {"tags": ["Inf", "Pass"], "word_form": "siktes"}, {"tags": ["Pres", "Pass"], "word_form": "siktes"}, {"tags": ["Past"], "word_form": "siktet"}, {"tags": ["<PerfPart>"], "word_form": "siktet"}, {"tags": ["Adj", "<PerfPart>", "Neuter", "Ind", "Sing"], "word_form": "siktet"}, {"tags": ["Adj", "<PerfPart>", "Masc/Fem", "Ind", "Sing"], "word_form": "siktet"}, {"tags": [], "word_form": null}, {"tags": ["Adj", "<PerfPart>", "Def", "Sing"], "word_form": "siktete"}, {"tags": ["Adj", "<PerfPart>", "Plur"], "word_form": "siktete"}, {"tags": ["Adj", "<PresPart>"], "word_form": "siktende"}, {"tags": ["Imp"], "word_form": "sikt"}, {"tags": [], "word_form": null}, {"tags": [], "word_form": null}], "inflection_group": "VERB_regular", "paradigm_id": 6, "standardisation": "STANDARD", "tags": ["VERB"], "to": null}, {"from": "1996-01-01", "inflection": [{"tags": ["Inf"], "word_form": "sikte"}, {"tags": [], "word_form": null}, {"tags": ["Pres"], "word_form": "sikter"}, {"tags": ["Inf", "Pass"], "word_form": "siktes"}, {"tags": ["Pres", "Pass"], "word_form": "siktes"}, {"tags": ["Past"], "word_form": "siktet"}, {"tags": ["<PerfPart>"], "word_form": "siktet"}, {"tags": ["Adj", "<PerfPart>", "Neuter", "Ind", "Sing"], "word_form": "siktet"}, {"tags": ["Adj", "<PerfPart>", "Masc/Fem", "Ind", "Sing"], "word_form": "siktet"}, {"tags": [], "word_form": null}, {"tags": ["Adj", "<PerfPart>", "Def", "Sing"], "word_form": "siktede"}, {"tags": ["Adj", "<PerfPart>", "Plur"], "word_form": "siktede"}, {"tags": ["Adj", "<PresPart>"], "word_form": "siktende"}, {"tags": ["Imp"], "word_form": "sikt"}, {"tags": [], "word_form": null}, {"tags": [], "word_form": null}], "inflection_group": "VERB_regular", "paradigm_id": 7, "standardisation": "STANDARD", "tags": ["VERB"], "to": null}], "split_inf": false}], "body": {"etymology": [{"type_": "etymology_reference", "content": "fra $", "items": [{"type_": "entity", "id": "l.ty."}]}], "definitions": [{"type_": "definition", "elements": [{"type_": "definition", "elements": [{"type_": "explanation", "content": "la gå gjennom en $ for å skille ut grovere bestanddeler", "items": [{"type_": "article_ref", "article_id": 51460, "lemmas": [{"type_": "lemma", "hgno": 1, "id": 59172, "lemma": "sikt"}], "definition_id": null}]}, {"type_": "example", "quote": {"content": "de $ melet", "items": [{"type_": "usage", "items": [], "text": "sikter"}]}, "explanation": {"content": "", "items": []}}], "id": 2, "sub_definition": false}, {"type_": "definition", "elements": [{"type_": "explanation", "content": "gå nøye gjennom for å velge ut", "items": []}, {"type_": "example", "quote": {"content": "søkerne til stillingen ble $ nøye", "items": [{"type_": "usage", "items": [], "text": "siktet"}]}, "explanation": {"content": "", "items": []}}], "id": 4, "sub_definition": false}], "id": 3, "sub_definition": false}]}, "to_index": ["sikter", "siktet"], "author": "15", "edit_state": "Eksisterende", "referers": [{"article_id": 14790, "hgno": 0, "lemma": "finsikte"}, {"article_id": 21077, "hgno": 0, "lemma": "grovsikte"}, {"article_id": 59203, "hgno": 0, "lemma": "sælde"}, {"article_id": 59457, "hgno": 0, "lemma": "sålde"}, {"article_id": 127661, "hgno": 2, "lemma": "sikting"}, {"article_id": 53529, "hgno": 0, "lemma": "skre"}, {"article_id": 51470, "hgno": 0, "lemma": "siktemel"}], "status": 8, "updated": "2024-11-29 07:51:48"}