{"article_id": 57572, "submitted": "2016-12-05 01:58:41", "suggest": ["stratosfærisk"], "lemmas": [{"final_lexeme": "stratosfærisk", "hgno": 0, "id": 65923, "inflection_class": "a2", "lemma": "stratosfærisk", "paradigm_info": [{"from": "2014-01-01", "inflection": [{"tags": ["Pos", "Masc/Fem", "Ind", "Sing"], "word_form": "stratosfærisk"}, {"tags": ["Pos", "Plur"], "word_form": "stratosfæriske"}, {"tags": ["Pos", "Def", "Sing"], "word_form": "stratosfæriske"}, {"tags": ["Pos", "Neuter", "Ind", "Sing"], "word_form": "stratosfærisk"}, {"tags": [], "word_form": null}, {"tags": [], "word_form": null}, {"tags": [], "word_form": null}], "inflection_group": "ADJ_regular", "paradigm_id": 452, "standardisation": "STANDARD", "tags": ["ADJ"], "to": null}], "split_inf": false}], "body": {"pronunciation": [], "definitions": [{"type_": "definition", "elements": [{"type_": "explanation", "content": "som gjelder statosfæren", "items": []}], "id": 2}]}, "author": "106", "edit_state": "Eksisterende", "referers": [], "status": 2, "updated": "2022-02-23 23:30:14"}