{"article_id": 58822, "submitted": "2016-12-05 01:59:06", "suggest": ["svor"], "lemmas": [{"final_lexeme": "svor", "hgno": 0, "id": 67310, "inflection_class": "m1", "lemma": "svor", "paradigm_info": [{"from": "1996-01-01", "inflection": [{"tags": ["Sing", "Ind"], "word_form": "svor"}, {"tags": ["Sing", "Def"], "word_form": "svoren"}, {"tags": ["Plur", "Ind"], "word_form": "svorer"}, {"tags": ["Plur", "Def"], "word_form": "svorene"}], "inflection_group": "NOUN_regular", "paradigm_id": 564, "standardisation": "STANDARD", "tags": ["NOUN", "Masc"], "to": null}], "split_inf": false}], "body": {"pronunciation": [], "etymology": [{"type_": "etymology_language", "content": "$ $", "items": [{"type_": "language", "id": "norr."}, {"type_": "usage", "text": "svǫrðr"}]}], "definitions": [{"type_": "definition", "elements": [{"type_": "explanation", "content": "hud, skinn på flesk", "items": []}, {"type_": "example", "quote": {"content": "fleske$", "items": [{"type_": "usage", "text": "svor"}]}, "explanation": {"content": "", "items": []}}], "id": 2}]}, "to_index": ["svǫrðr", "svor"], "author": "106", "edit_state": "Eksisterende", "referers": [{"article_id": 15373, "hgno": 0, "lemma": "fleskesvor"}], "status": 2, "updated": "2022-02-23 23:30:14"}