{"article_id": 62501, "submitted": "2019-01-08 07:54:26", "suggest": ["trossig"], "lemmas": [{"final_lexeme": "trossig", "hgno": 0, "id": 71478, "inflection_class": "a2", "lemma": "trossig", "paradigm_info": [{"from": "2014-01-01", "inflection": [{"tags": ["Pos", "Masc/Fem", "Ind", "Sing"], "word_form": "trossig"}, {"tags": ["Pos", "Plur"], "word_form": "trossige"}, {"tags": ["Pos", "Def", "Sing"], "word_form": "trossige"}, {"tags": ["Pos", "Neuter", "Ind", "Sing"], "word_form": "trossig"}, {"tags": [], "word_form": null}, {"tags": [], "word_form": null}, {"tags": [], "word_form": null}], "inflection_group": "ADJ_regular", "paradigm_id": 452, "standardisation": "STANDARD", "tags": ["ADJ"], "to": null}], "split_inf": false}], "body": {"pronunciation": [], "etymology": [{"type_": "etymology_reference", "content": "av $", "items": [{"type_": "article_ref", "article_id": 62493, "lemmas": [{"type_": "lemma", "hgno": 1, "id": 71469, "lemma": "tross"}], "definition_id": null}]}, {"type_": "etymology_reference", "content": "$ $", "items": [{"type_": "relation", "id": "sm_o_s"}, {"type_": "article_ref", "article_id": 61933, "lemmas": [{"type_": "lemma", "hgno": 0, "id": 70824, "lemma": "trassig"}], "definition_id": null}]}], "definitions": [{"type_": "definition", "elements": [{"type_": "explanation", "content": "$", "items": [{"type_": "article_ref", "article_id": 64060, "lemmas": [{"type_": "lemma", "hgno": 0, "id": 73379, "lemma": "ukuelig"}], "definition_id": null}]}, {"type_": "example", "quote": {"content": "en $ natur", "items": [{"type_": "usage", "text": "trossig"}]}, "explanation": {"content": "", "items": []}}, {"type_": "example", "quote": {"content": "et $ blikk", "items": [{"type_": "usage", "text": "trossig"}]}, "explanation": {"content": "", "items": []}}], "id": 2}]}, "to_index": ["trossig", "trossig"], "author": "106", "edit_state": "Eksisterende", "referers": [], "status": 5, "updated": "2022-02-23 23:30:14"}