{"article_id": 66505, "submitted": "2016-12-05 02:01:28", "suggest": ["vannledning", "vassledning"], "lemmas": [{"final_lexeme": "ledning", "hgno": 0, "id": 76397, "inflection_class": "m1, f1", "initial_lexeme": "vann", "lemma": "vannledning", "paradigm_info": [{"from": "1996-01-01", "inflection": [{"tags": ["Sing", "Ind"], "word_form": "vannledning"}, {"tags": ["Sing", "Def"], "word_form": "vannledningen"}, {"tags": ["Plur", "Ind"], "word_form": "vannledninger"}, {"tags": ["Plur", "Def"], "word_form": "vannledningene"}], "inflection_group": "NOUN_regular", "paradigm_id": 564, "standardisation": "STANDARD", "tags": ["NOUN", "Masc"], "to": null}, {"from": "1996-01-01", "inflection": [{"tags": ["Sing", "Ind"], "word_form": "vannledning"}, {"tags": ["Sing", "Def"], "word_form": "vannledninga"}, {"tags": ["Plur", "Ind"], "word_form": "vannledninger"}, {"tags": ["Plur", "Def"], "word_form": "vannledningene"}], "inflection_group": "NOUN_regular", "paradigm_id": 760, "standardisation": "STANDARD", "tags": ["NOUN", "Fem"], "to": null}], "split_inf": false}, {"final_lexeme": "ledning", "hgno": 0, "id": 77098, "inflection_class": "m1, f1", "initial_lexeme": "vass", "lemma": "vassledning", "paradigm_info": [{"from": "1996-01-01", "inflection": [{"tags": ["Sing", "Ind"], "word_form": "vassledning"}, {"tags": ["Sing", "Def"], "word_form": "vassledningen"}, {"tags": ["Plur", "Ind"], "word_form": "vassledninger"}, {"tags": ["Plur", "Def"], "word_form": "vassledningene"}], "inflection_group": "NOUN_regular", "paradigm_id": 564, "standardisation": "STANDARD", "tags": ["NOUN", "Masc"], "to": null}, {"from": "1996-01-01", "inflection": [{"tags": ["Sing", "Ind"], "word_form": "vassledning"}, {"tags": ["Sing", "Def"], "word_form": "vassledninga"}, {"tags": ["Plur", "Ind"], "word_form": "vassledninger"}, {"tags": ["Plur", "Def"], "word_form": "vassledningene"}], "inflection_group": "NOUN_regular", "paradigm_id": 760, "standardisation": "STANDARD", "tags": ["NOUN", "Fem"], "to": null}], "split_inf": false}], "body": {"pronunciation": [], "definitions": [{"type_": "definition", "elements": [{"type_": "explanation", "content": "(nett av) rør som fører vann fram til tappingsstedet", "items": []}], "id": 2}]}, "author": "106", "edit_state": "Eksisterende", "referers": [{"article_id": 34217, "hgno": 0, "lemma": "ledning"}, {"article_id": 66537, "hgno": 0, "lemma": "vannrør"}], "status": 2, "updated": "2022-02-23 23:30:14"}