{"article_id": 9968, "submitted": "2021-07-22 14:18:00", "suggest": ["di-"], "lemmas": [{"final_lexeme": "di-", "hgno": 2, "id": 11693, "lemma": "di-", "paradigm_info": [{"from": "1996-01-01", "inflection": [{"tags": [], "word_form": "di-"}], "inflection_group": "PFX", "paradigm_id": 41, "standardisation": "STANDARD", "tags": ["PFX"], "to": null}], "split_inf": false}], "body": {"pronunciation": [], "etymology": [{"type_": "etymology_reference", "content": "form av $", "items": [{"type_": "article_ref", "article_id": 10238, "lemmas": [{"type_": "lemma", "hgno": 0, "id": 11978, "lemma": "dis-"}], "definition_id": null}]}], "definitions": [{"type_": "definition", "elements": [{"type_": "explanation", "content": "$ brukt til å markere atskillelse eller motsetning", "items": [{"type_": "article_ref", "article_id": 45949, "lemmas": [{"type_": "lemma", "hgno": 0, "id": 52955, "lemma": "prefiks"}], "definition_id": 2, "definition_order": 1}]}, {"type_": "explanation", "content": "i ord som $, $ og $", "items": [{"type_": "article_ref", "article_id": 10070, "lemmas": [{"type_": "lemma", "hgno": 0, "id": 11801, "lemma": "diffus"}], "definition_id": null}, {"type_": "article_ref", "article_id": 10151, "lemmas": [{"type_": "lemma", "hgno": 0, "id": 11886, "lemma": "dimensjon"}], "definition_id": null}, {"type_": "article_ref", "article_id": 10397, "lemmas": [{"type_": "lemma", "hgno": 0, "id": 12140, "lemma": "dividere"}], "definition_id": null}]}], "id": 2}]}, "author": "14", "edit_state": "Eksisterende", "referers": [{"article_id": 10096, "hgno": 0, "lemma": "digresjon"}, {"article_id": 10151, "hgno": 0, "lemma": "dimensjon"}, {"article_id": 10162, "hgno": 0, "lemma": "dimittere"}, {"article_id": 10228, "hgno": 0, "lemma": "dirigere"}, {"article_id": 10238, "hgno": 0, "lemma": "dis-"}, {"article_id": 10388, "hgno": 0, "lemma": "divergere"}, {"article_id": 10392, "hgno": 0, "lemma": "divertere"}], "status": 8, "updated": "2022-02-23 23:30:14"}