{"article_id": 101688, "submitted": "2016-12-05 02:03:28", "suggest": ["fade ut"], "lemmas": [{"final_lexeme": "fade ut", "hgno": 0, "id": 1144571, "lemma": "fade ut", "mo_link": 0, "paradigm_info": [{"from": "2019-01-01", "inflection": [{"tags": [], "word_form": "fade ut"}], "inflection_group": "EXPR", "paradigm_id": 2470, "standardisation": "REGISTERED", "tags": ["EXPR"], "to": null}], "split_inf": false, "stress_vowel": 0}], "body": {"pronunciation": [], "definitions": [{"type_": "definition", "elements": [{"type_": "definition", "elements": [{"type_": "explanation", "content": "gradvis dempe eller bli dempet", "items": []}, {"type_": "example", "quote": {"content": "fade ut en låt i det den neste tar over", "items": []}, "explanation": {"content": "", "items": []}}], "id": 2}, {"type_": "definition", "elements": [{"type_": "explanation", "content": "miste interessen eller oppmerksomheten", "items": []}, {"type_": "example", "quote": {"content": "foredraget var så kjedelig at jeg fadet ut av og til", "items": []}, "explanation": {"content": "", "items": []}}], "id": 4}, {"type_": "definition", "elements": [{"type_": "explanation", "content": "forsvinne", "items": []}, {"type_": "explanation", "content": "dø ut", "items": []}, {"type_": "example", "quote": {"content": "forholdet er i ferd med å fade ut", "items": []}, "explanation": {"content": "", "items": []}}], "id": 5}, {"type_": "explanation", "content": "Se: $", "items": [{"type_": "article_ref", "article_id": 13551, "lemmas": [{"lemma": "fade"}]}]}], "id": 3}]}, "author": "USD_LEKS_BOKMAALSORDBOKA", "edit_state": "Eksisterende", "referers": [{"article_id": 13551, "hgno": 0, "lemma": "fade"}], "status": 8, "updated": "2022-02-23 23:30:14"}