{"article_id": 1125, "submitted": "2024-11-25 06:15:27", "suggest": ["årsgammel", "årsgammal"], "lemmas": [{"added_norm": false, "final_lexeme": "gammel", "hgno": 0, "id": 80686, "initial_lexeme": "år", "junction": "s", "lemma": "årsgammel", "paradigm_info": [{"from": "1996-01-01", "inflection": [{"tags": ["Pos", "Masc/Fem", "Ind", "Sing"], "word_form": "årsgammel"}, {"tags": ["Pos", "Plur"], "word_form": "årsgamle"}, {"tags": ["Pos", "Def", "Sing"], "word_form": "årsgamle"}, {"tags": ["Pos", "Neuter", "Ind", "Sing"], "word_form": "årsgammelt"}, {"tags": [], "word_form": null}, {"tags": [], "word_form": null}, {"tags": [], "word_form": null}], "inflection_group": "ADJ_regular", "paradigm_id": 506, "standardisation": "STANDARD", "tags": ["ADJ"], "to": null}], "split_inf": false}, {"added_norm": false, "final_lexeme": "gammal", "hgno": 0, "id": 82159, "initial_lexeme": "år", "junction": "s", "lemma": "årsgammal", "paradigm_info": [{"from": "1996-01-01", "inflection": [{"tags": ["Pos", "Masc/Fem", "Ind", "Sing"], "word_form": "årsgammal"}, {"tags": ["Pos", "Plur"], "word_form": "årsgamle"}, {"tags": ["Pos", "Def", "Sing"], "word_form": "årsgamle"}, {"tags": ["Pos", "Neuter", "Ind", "Sing"], "word_form": "årsgammalt"}, {"tags": [], "word_form": null}, {"tags": [], "word_form": null}, {"tags": [], "word_form": null}], "inflection_group": "ADJ_regular", "paradigm_id": 505, "standardisation": "STANDARD", "tags": ["ADJ"], "to": null}], "split_inf": false}], "body": {"definitions": [{"type_": "definition", "elements": [{"type_": "explanation", "content": "som er ett år gammel", "items": [], "attest": []}, {"type_": "example", "quote": {"content": "en årsgammel elgkalv", "items": []}, "explanation": {"content": "", "items": []}, "attest": []}], "id": 2, "sub_definition": false}]}, "author": "14", "edit_state": "Eksisterende", "referers": [], "status": 8, "updated": "2024-12-18 08:42:18"}