{"article_id": 11682, "submitted": "2021-06-29 15:52:03", "suggest": ["edru"], "lemmas": [{"final_lexeme": "edru", "hgno": 0, "id": 13628, "inflection_class": "a3, a2", "lemma": "edru", "paradigm_info": [{"from": "2014-01-01", "inflection": [{"tags": ["Pos", "Masc/Fem", "Ind", "Sing"], "word_form": "edru"}, {"tags": ["Pos", "Plur"], "word_form": "edru"}, {"tags": ["Pos", "Def", "Sing"], "word_form": "edru"}, {"tags": ["Pos", "Neuter", "Ind", "Sing"], "word_form": "edru"}, {"tags": [], "word_form": null}, {"tags": [], "word_form": null}, {"tags": [], "word_form": null}], "inflection_group": "ADJ_regular", "paradigm_id": 447, "standardisation": "STANDARD", "tags": ["ADJ"], "to": null}, {"from": "2014-01-01", "inflection": [{"tags": ["Pos", "Masc/Fem", "Ind", "Sing"], "word_form": "edru"}, {"tags": ["Pos", "Plur"], "word_form": "edrue"}, {"tags": ["Pos", "Def", "Sing"], "word_form": "edrue"}, {"tags": ["Pos", "Neuter", "Ind", "Sing"], "word_form": "edru"}, {"tags": [], "word_form": null}, {"tags": [], "word_form": null}, {"tags": [], "word_form": null}], "inflection_group": "ADJ_regular", "paradigm_id": 452, "standardisation": "STANDARD", "tags": ["ADJ"], "to": null}], "split_inf": false}], "body": {"pronunciation": [], "etymology": [{"type_": "etymology_language", "content": "førsteleddet av $ $ ‘alltid’", "items": [{"type_": "language", "id": "norr."}, {"type_": "usage", "text": "æ"}]}, {"type_": "etymology_reference", "content": "etterleddet $ med $", "items": [{"type_": "relation", "id": "besl"}, {"type_": "article_ref", "article_id": 11057, "lemmas": [{"type_": "lemma", "hgno": 0, "id": 12903, "lemma": "drøy"}, {"type_": "lemma", "hgno": 0, "id": 12835, "lemma": "dryg"}], "definition_id": null}]}], "definitions": [{"type_": "definition", "elements": [{"type_": "explanation", "content": "ikke påvirket av alkohol", "items": []}, {"type_": "example", "quote": {"content": "er han $?", "items": [{"type_": "usage", "text": "edru"}]}, "explanation": {"content": "", "items": []}}, {"type_": "example", "quote": {"content": "bli $ igjen", "items": [{"type_": "usage", "text": "edru"}]}, "explanation": {"content": "", "items": []}}, {"type_": "example", "quote": {"content": "være klinkende $", "items": [{"type_": "usage", "text": "edru"}]}, "explanation": {"content": "", "items": []}}, {"type_": "example", "quote": {"content": "i $ tilstand", "items": [{"type_": "usage", "text": "edru"}]}, "explanation": {"content": "", "items": []}}], "id": 2}]}, "to_index": ["æ", "edru", "edru", "edru", "edru"], "author": "15", "edit_state": "Eksisterende", "referers": [{"article_id": 3734, "hgno": 0, "lemma": "avruse"}, {"article_id": 41631, "hgno": 0, "lemma": "nøktern"}], "status": 8, "updated": "2022-02-23 23:30:14"}