{"article_id": 133835, "submitted": "2024-06-27 12:29:17", "suggest": ["ungfugl"], "lemmas": [{"added_norm": false, "final_lexeme": "fugl", "hgno": 0, "id": 150490, "inflection_class": "m1", "initial_lexeme": "ung", "lemma": "ungfugl", "paradigm_info": [{"from": "1996-01-01", "inflection": [{"tags": ["Sing", "Ind"], "word_form": "ungfugl"}, {"tags": ["Sing", "Def"], "word_form": "ungfuglen"}, {"tags": ["Plur", "Ind"], "word_form": "ungfugler"}, {"tags": ["Plur", "Def"], "word_form": "ungfuglene"}], "inflection_group": "NOUN_regular", "paradigm_id": 564, "standardisation": "STANDARD", "tags": ["NOUN", "Masc"], "to": null}], "split_inf": false}], "body": {"definitions": [{"type_": "definition", "elements": [{"type_": "explanation", "content": "ung fugl som ikke har hekket", "items": [], "attest": []}, {"type_": "example", "quote": {"content": "fjærdrakten tyder på at det er en ungfugl", "items": []}, "explanation": {"content": "", "items": []}, "attest": []}], "id": 1, "sub_definition": false}]}, "author": "14", "edit_state": "Ny", "referers": [], "status": 8, "updated": "2024-12-18 08:18:12"}