{"article_id": 19655, "submitted": "2016-12-05 01:46:55", "suggest": ["gipsmaske"], "lemmas": [{"final_lexeme": "maske", "hgno": 0, "id": 22938, "initial_lexeme": "gips", "lemma": "gipsmaske", "paradigm_info": [{"from": "1996-01-01", "inflection": [{"tags": ["Sing", "Ind"], "word_form": "gipsmaske"}, {"tags": ["Sing", "Def"], "word_form": "gipsmasken"}, {"tags": ["Plur", "Ind"], "word_form": "gipsmasker"}, {"tags": ["Plur", "Def"], "word_form": "gipsmaskene"}], "inflection_group": "NOUN_regular", "paradigm_id": 566, "standardisation": "STANDARD", "tags": ["NOUN", "Masc"], "to": null}, {"from": "1996-01-01", "inflection": [{"tags": ["Sing", "Ind"], "word_form": "gipsmaske"}, {"tags": ["Sing", "Def"], "word_form": "gipsmaska"}, {"tags": ["Plur", "Ind"], "word_form": "gipsmasker"}, {"tags": ["Plur", "Def"], "word_form": "gipsmaskene"}], "inflection_group": "NOUN_regular", "paradigm_id": 762, "standardisation": "STANDARD", "tags": ["NOUN", "Fem"], "to": null}]}], "body": {"pronunciation": [], "definitions": []}}