{"article_id": 20672, "submitted": "2020-11-13 08:57:42", "suggest": ["grann"], "lemmas": [{"final_lexeme": "grann", "hgno": 2, "id": 24129, "lemma": "grann", "paradigm_info": [{"from": "1996-01-01", "inflection": [{"tags": ["Pos", "Masc/Fem", "Ind", "Sing"], "word_form": "grann"}, {"tags": ["Pos", "Plur"], "word_form": "granne"}, {"tags": ["Pos", "Def", "Sing"], "word_form": "granne"}, {"tags": ["Pos", "Neuter", "Ind", "Sing"], "word_form": "grant"}, {"tags": ["Cmp"], "word_form": "grannere"}, {"tags": ["Sup", "Ind"], "word_form": "grannest"}, {"tags": ["Sup", "Def"], "word_form": "granneste"}], "inflection_group": "ADJ_regular", "paradigm_id": 458, "standardisation": "STANDARD", "tags": ["ADJ"], "to": null}], "split_inf": false}], "body": {"pronunciation": [], "etymology": [{"type_": "etymology_language", "content": "$ $", "items": [{"type_": "language", "id": "norr."}, {"type_": "usage", "text": "grannr"}]}, {"type_": "etymology_reference", "content": "$ med $", "items": [{"type_": "relation", "id": "besl"}, {"type_": "article_ref", "article_id": 20637, "lemmas": [{"type_": "lemma", "hgno": 0, "id": 24093, "lemma": "gran"}], "definition_id": null}]}], "definitions": [{"type_": "definition", "elements": [{"type_": "definition", "elements": [{"type_": "explanation", "content": "$, $, $", "items": [{"type_": "article_ref", "article_id": 63231, "lemmas": [{"type_": "lemma", "hgno": 0, "id": 72344, "lemma": "tynn"}], "definition_id": 2, "definition_order": 1}, {"type_": "article_ref", "article_id": 54713, "lemmas": [{"type_": "lemma", "hgno": 0, "id": 63047, "lemma": "smal"}], "definition_id": 5, "definition_order": 0}, {"type_": "article_ref", "article_id": 14683, "lemmas": [{"type_": "lemma", "hgno": 0, "id": 16991, "lemma": "fin"}], "definition_id": 22, "definition_order": 7}]}, {"type_": "example", "quote": {"content": "$ tråd", "items": [{"type_": "usage", "text": "grann"}]}, "explanation": {"content": "", "items": []}}, {"type_": "example", "quote": {"content": "være $ i målet", "items": [{"type_": "usage", "text": "grann"}]}, "explanation": {"content": "", "items": []}}], "id": 2}, {"type_": "definition", "elements": [{"type_": "explanation", "content": "$", "items": [{"type_": "article_ref", "article_id": 41655, "lemmas": [{"type_": "lemma", "hgno": 1, "id": 48787, "lemma": "nøye"}], "definition_id": null}]}, {"type_": "definition", "elements": [{"type_": "explanation", "content": "brukt som adverb: tydelig", "items": []}, {"type_": "example", "quote": {"content": "jeg husker så grant den dagen", "items": []}, "explanation": {"content": "", "items": []}}], "id": 4, "sub_definition": true}], "id": 5}], "id": 3}]}, "to_index": ["grannr", "grann", "grann"], "author": "13", "edit_state": "Eksisterende", "referers": [{"article_id": 20637, "hgno": 0, "lemma": "gran"}, {"article_id": 20683, "hgno": 0, "lemma": "granske"}], "status": 8, "updated": "2022-03-29 07:34:43"}