{"article_id": 25853, "submitted": "2021-11-10 14:09:18", "suggest": ["ilske"], "lemmas": [{"final_lexeme": "ilske", "hgno": 1, "id": 30828, "inflection_class": "m1, f1", "lemma": "ilske", "paradigm_info": [{"from": "1996-01-01", "inflection": [{"tags": ["Sing", "Ind"], "word_form": "ilske"}, {"tags": ["Sing", "Def"], "word_form": "ilsken"}, {"tags": ["Plur", "Ind"], "word_form": "ilsker"}, {"tags": ["Plur", "Def"], "word_form": "ilskene"}], "inflection_group": "NOUN_regular", "paradigm_id": 566, "standardisation": "STANDARD", "tags": ["NOUN", "Masc"], "to": null}, {"from": "1996-01-01", "inflection": [{"tags": ["Sing", "Ind"], "word_form": "ilske"}, {"tags": ["Sing", "Def"], "word_form": "ilska"}, {"tags": ["Plur", "Ind"], "word_form": "ilsker"}, {"tags": ["Plur", "Def"], "word_form": "ilskene"}], "inflection_group": "NOUN_regular", "paradigm_id": 762, "standardisation": "STANDARD", "tags": ["NOUN", "Fem"], "to": null}], "split_inf": false}], "body": {"pronunciation": [], "etymology": [{"type_": "etymology_language", "content": "$ $", "items": [{"type_": "language", "id": "norr."}, {"type_": "usage", "text": "illska"}]}], "definitions": [{"type_": "definition", "elements": [{"type_": "explanation", "content": "harme, indignasjon, sinne", "items": []}, {"type_": "example", "quote": {"content": "skrike av $", "items": [{"type_": "usage", "text": "ilske"}]}, "explanation": {"content": "", "items": []}}], "id": 2}]}, "to_index": ["illska", "ilske"], "author": "15", "edit_state": "Eksisterende", "referers": [{"article_id": 25855, "hgno": 0, "lemma": "ilsken"}], "status": 8, "updated": "2022-09-27 07:26:20"}