{"article_id": 2936, "submitted": "2021-03-05 13:09:32", "suggest": ["aspiratorisk"], "lemmas": [{"final_lexeme": "aspiratorisk", "hgno": 0, "id": 3495, "inflection_class": "a2", "lemma": "aspiratorisk", "paradigm_info": [{"from": "2014-01-01", "inflection": [{"tags": ["Pos", "Masc/Fem", "Ind", "Sing"], "word_form": "aspiratorisk"}, {"tags": ["Pos", "Plur"], "word_form": "aspiratoriske"}, {"tags": ["Pos", "Def", "Sing"], "word_form": "aspiratoriske"}, {"tags": ["Pos", "Neuter", "Ind", "Sing"], "word_form": "aspiratorisk"}, {"tags": [], "word_form": null}, {"tags": [], "word_form": null}, {"tags": [], "word_form": null}], "inflection_group": "ADJ_regular", "paradigm_id": 452, "standardisation": "STANDARD", "tags": ["ADJ"], "to": null}], "split_inf": false}], "body": {"pronunciation": [{"type_": "pronunciation", "content": "aspiratoˊrisk", "items": []}], "definitions": [{"type_": "definition", "elements": [{"type_": "explanation", "content": "$: uttalt med $", "items": [{"type_": "domain", "id": "i_spraakv"}, {"type_": "article_ref", "article_id": 108705, "lemmas": [{"type_": "lemma", "hgno": 0, "id": 161805, "lemma": "pustelyd"}], "definition_id": null}]}, {"type_": "explanation", "content": "$ $", "items": [{"type_": "relation", "id": "jf"}, {"type_": "article_ref", "article_id": 2934, "lemmas": [{"type_": "lemma", "hgno": 0, "id": 3493, "lemma": "aspirasjon"}], "definition_id": 4, "definition_order": 2}]}], "id": 2}]}, "author": "18", "edit_state": "Eksisterende", "referers": [], "status": 8, "updated": "2022-02-23 23:30:14"}