{"article_id": 41696, "submitted": "2024-09-04 14:40:31", "suggest": ["nål"], "lemmas": [{"added_norm": false, "final_lexeme": "nål", "hgno": 0, "id": 48525, "inflection_class": "m1, f1", "lemma": "nål", "paradigm_info": [{"from": "1996-01-01", "inflection": [{"tags": ["Sing", "Ind"], "word_form": "nål"}, {"tags": ["Sing", "Def"], "word_form": "nåla"}, {"tags": ["Plur", "Ind"], "word_form": "nåler"}, {"tags": ["Plur", "Def"], "word_form": "nålene"}], "inflection_group": "NOUN_regular", "paradigm_id": 760, "standardisation": "STANDARD", "tags": ["NOUN", "Fem"], "to": null}, {"from": "1996-01-01", "inflection": [{"tags": ["Sing", "Ind"], "word_form": "nål"}, {"tags": ["Sing", "Def"], "word_form": "nålen"}, {"tags": ["Plur", "Ind"], "word_form": "nåler"}, {"tags": ["Plur", "Def"], "word_form": "nålene"}], "inflection_group": "NOUN_regular", "paradigm_id": 564, "standardisation": "STANDARD", "tags": ["NOUN", "Masc"], "to": null}], "split_inf": false}], "body": {"etymology": [{"type_": "etymology_reference", "content": "$ $", "items": [{"type_": "entity", "id": "norr."}, {"type_": "usage", "text": "nál"}]}], "definitions": [{"type_": "definition", "elements": [{"type_": "definition", "elements": [{"type_": "explanation", "content": "tynt, spisst redskap til å sy, stoppe eller hekle med $ til å feste noe med", "items": [{"type_": "entity", "id": "el"}], "attest": []}, {"type_": "example", "quote": {"content": "bruke $ og tråd", "items": [{"type_": "usage", "text": "nål"}]}, "explanation": {"content": "", "items": []}, "attest": []}, {"type_": "example", "quote": {"content": "træ i en $", "items": [{"type_": "usage", "text": "nål"}]}, "explanation": {"content": "", "items": []}, "attest": []}, {"type_": "example", "quote": {"content": "feste noe med en nål", "items": []}, "explanation": {"content": "", "items": []}, "attest": []}, {"type_": "sub_article", "article_id": 104173, "lemmas": ["ikke eie nåla i veggen"], "article": {"type_": "article", "article_id": 104173, "lemmas": [{"type_": "lemma", "hgno": 0, "id": 1145907, "lemma": "ikke eie nåla i veggen"}], "body": {"pronunciation": [], "definitions": [{"type_": "definition", "elements": [{"type_": "explanation", "content": "være lutfattig", "items": []}], "id": 2}]}, "article_type": "SUB_ARTICLE", "author": "162", "dict_id": "BM", "frontpage": false, "latest_status": 8, "owner": "179", "properties": {"edit_state": "Eksisterende"}, "referenced_by": [{"art_id": 41696, "hgno": 0, "word_form": "nål"}], "updated": null, "version": 2, "word_class": "EXPR"}, "intro": {"content": "", "items": []}}, {"type_": "sub_article", "article_id": 104174, "lemmas": ["lete etter nåla i høystakken"], "article": {"type_": "article", "article_id": 104174, "lemmas": [{"type_": "lemma", "hgno": 0, "id": 1145908, "lemma": "lete etter nåla i høystakken"}], "body": {"definitions": [{"type_": "definition", "elements": [{"type_": "explanation", "content": "lete etter noe lite i en stor mengde", "items": []}], "id": 2, "sub_definition": false}]}, "article_type": "SUB_ARTICLE", "author": "14", "dict_id": "BM", "frontpage": false, "latest_status": 8, "owner": "179", "properties": {"edit_state": "Eksisterende"}, "referenced_by": [{"art_id": 25349, "hgno": 0, "word_form": "høystakk"}, {"art_id": 41696, "hgno": 0, "word_form": "nål"}], "updated": null, "version": 3, "word_class": "EXPR"}, "intro": {"content": "", "items": []}}, {"type_": "sub_article", "article_id": 123612, "lemmas": ["[gå|sitte|stå] på nåler"], "article": {"type_": "article", "article_id": 123612, "lemmas": [{"type_": "lemma", "hgno": 0, "id": 2007739, "lemma": "[gå|sitte|stå] på nåler"}], "body": {"definitions": [{"type_": "definition", "elements": [{"type_": "explanation", "content": "være urolig, spent, nervøs", "items": [], "attest": []}, {"type_": "example", "quote": {"content": "de ansatte går på nåler rundt sjefen", "items": []}, "explanation": {"content": "", "items": []}, "attest": []}, {"type_": "example", "quote": {"content": "hun satt på nåler mens hun ventet på svar", "items": []}, "explanation": {"content": "", "items": []}, "attest": []}, {"type_": "example", "quote": {"content": "hoffet stod som på nåler", "items": []}, "explanation": {"content": "", "items": []}, "attest": []}], "id": 1, "sub_definition": false}]}, "article_type": "SUB_ARTICLE", "author": "179", "dict_id": "BM", "frontpage": false, "latest_status": 8, "owner": "179", "properties": null, "referenced_by": [{"art_id": 41696, "hgno": 0, "word_form": "nål"}], "updated": null, "version": 2, "word_class": "EXPR"}, "intro": {"content": "", "items": []}}, {"type_": "compound_list", "elements": [{"type_": "article_ref", "article_id": 22916, "lemmas": [{"type_": "lemma", "hgno": 0, "id": 26992, "lemma": "heklenål"}]}, {"type_": "article_ref", "article_id": 70301, "lemmas": [{"type_": "lemma", "hgno": 0, "id": 157735, "lemma": "hårnål"}]}, {"type_": "article_ref", "article_id": 30428, "lemmas": [{"type_": "lemma", "hgno": 0, "id": 35866, "lemma": "knappenål"}]}, {"type_": "article_ref", "article_id": 59135, "lemmas": [{"type_": "lemma", "hgno": 0, "id": 67705, "lemma": "synål"}]}], "intro": {"content": "som etterledd i ord som", "items": []}}], "id": 2, "sub_definition": false}, {"type_": "definition", "elements": [{"type_": "explanation", "content": "del av $ til å stikke inn i kroppen for å sprøyte inn medisin", "items": [{"type_": "article_ref", "article_id": 28586, "lemmas": [{"type_": "lemma", "hgno": 0, "id": 33821, "lemma": "kanyle"}], "definition_id": 2, "definition_order": 1}], "attest": []}], "id": 3, "sub_definition": false}, {"type_": "definition", "elements": [{"type_": "explanation", "content": "smykke eller merke til å feste med en $", "items": [{"type_": "article_ref", "article_id": 41696, "lemmas": [{"type_": "lemma", "hgno": 0, "id": 48525, "lemma": "nål"}], "definition_id": 2, "definition_order": 1}], "attest": []}, {"type_": "example", "quote": {"content": "ha en nål på jakkeslaget", "items": []}, "explanation": {"content": "", "items": []}, "attest": []}, {"type_": "compound_list", "elements": [{"type_": "article_ref", "article_id": 7864, "lemmas": [{"type_": "lemma", "hgno": 0, "id": 9349, "lemma": "brystnål"}]}, {"type_": "article_ref", "article_id": 54485, "lemmas": [{"type_": "lemma", "hgno": 0, "id": 62779, "lemma": "slipsnål"}]}], "intro": {"content": "som etterledd i ord som", "items": []}}], "id": 1, "sub_definition": false}, {"type_": "definition", "elements": [{"type_": "explanation", "content": "$", "items": [{"type_": "article_ref", "article_id": 68739, "lemmas": [{"type_": "lemma", "hgno": 0, "id": 79345, "lemma": "viser"}]}], "attest": []}, {"type_": "example", "quote": {"content": "nåla på speedometeret viste 90 km/t", "items": []}, "explanation": {"content": "", "items": []}, "attest": []}, {"type_": "compound_list", "elements": [{"type_": "article_ref", "article_id": 31028, "lemmas": [{"type_": "lemma", "hgno": 0, "id": 36546, "lemma": "kompassnål"}]}, {"type_": "article_ref", "article_id": 36565, "lemmas": [{"type_": "lemma", "hgno": 0, "id": 42937, "lemma": "magnetnål"}]}], "intro": {"content": "som etterledd i ord som", "items": []}}], "id": 7, "sub_definition": false}, {"type_": "definition", "elements": [{"type_": "explanation", "content": "noe som ligner en $", "items": [{"type_": "article_ref", "article_id": 41696, "lemmas": [{"type_": "lemma", "hgno": 0, "id": 48525, "lemma": "nål"}], "definition_id": 2, "definition_order": 1}], "attest": []}, {"type_": "example", "quote": {"content": "$ på juletreet drysset", "items": [{"type_": "usage", "text": "nålene"}]}, "explanation": {"content": "", "items": []}, "attest": []}, {"type_": "compound_list", "elements": [{"type_": "article_ref", "article_id": 4623, "lemmas": [{"type_": "lemma", "hgno": 0, "id": 5449, "lemma": "barnål"}]}, {"type_": "article_ref", "article_id": 18443, "lemmas": [{"type_": "lemma", "hgno": 0, "id": 21564, "lemma": "furunål"}]}, {"type_": "article_ref", "article_id": 27278, "lemmas": [{"type_": "lemma", "hgno": 0, "id": 32386, "lemma": "isnål"}]}], "intro": {"content": "som etterledd i ord som", "items": []}}], "id": 5, "sub_definition": false}], "id": 4, "sub_definition": false}]}, "to_index": ["nál", "nål", "nål", "nålene"], "author": "179", "edit_state": "Eksisterende", "referers": [{"article_id": 4623, "hgno": 0, "lemma": "barnål"}, {"article_id": 70301, "hgno": 0, "lemma": "hårnål"}, {"article_id": 30428, "hgno": 0, "lemma": "knappenål"}, {"article_id": 41696, "hgno": 0, "lemma": "nål"}, {"article_id": 40217, "hgno": 0, "lemma": "nat"}, {"article_id": 129536, "hgno": 0, "lemma": "pyntenål"}, {"article_id": 28412, "hgno": 0, "lemma": "kaménål"}], "status": 8, "updated": "2024-09-04 14:41:19"}