{"article_id": 46340, "submitted": "2022-12-02 11:53:27", "suggest": ["produksjon"], "lemmas": [{"final_lexeme": "produksjon", "hgno": 0, "id": 53354, "inflection_class": "m1", "lemma": "produksjon", "paradigm_info": [{"from": "1996-01-01", "inflection": [{"tags": ["Sing", "Ind"], "word_form": "produksjon"}, {"tags": ["Sing", "Def"], "word_form": "produksjonen"}, {"tags": ["Plur", "Ind"], "word_form": "produksjoner"}, {"tags": ["Plur", "Def"], "word_form": "produksjonene"}], "inflection_group": "NOUN_regular", "paradigm_id": 564, "standardisation": "STANDARD", "tags": ["NOUN", "Masc"], "to": null}], "split_inf": false}], "body": {"etymology": [{"type_": "etymology_reference", "content": "fra $, $ $", "items": [{"type_": "entity", "id": "lat."}, {"type_": "entity", "id": "jf"}, {"type_": "article_ref", "article_id": 46363, "lemmas": [{"type_": "lemma", "hgno": 0, "id": 53379, "lemma": "produsere"}], "definition_id": null}]}], "definitions": [{"type_": "definition", "elements": [{"type_": "definition", "elements": [{"type_": "explanation", "content": "det å produsere noe", "items": []}, {"type_": "explanation", "content": "$, $", "items": [{"type_": "article_ref", "article_id": 17573, "lemmas": [{"type_": "lemma", "hgno": 0, "id": 20434, "lemma": "framstilling"}, {"type_": "lemma", "hgno": 0, "id": 20935, "lemma": "fremstilling"}], "definition_id": 4, "definition_order": 2}, {"type_": "article_ref", "article_id": 61009, "lemmas": [{"type_": "lemma", "hgno": 0, "id": 69780, "lemma": "tilvirking"}, {"type_": "lemma", "hgno": 0, "id": 69781, "lemma": "tilvirkning"}], "definition_id": null}]}, {"type_": "example", "quote": {"content": "sette en ny vare i $", "items": [{"type_": "usage", "items": [], "text": "produksjon"}]}, "explanation": {"content": "", "items": []}}, {"type_": "example", "quote": {"content": "modellen er gått ut av $", "items": [{"type_": "usage", "items": [], "text": "produksjon"}]}, "explanation": {"content": "", "items": []}}, {"type_": "example", "quote": {"content": "arbeide i $", "items": [{"type_": "usage", "items": [], "text": "produksjonen"}]}, "explanation": {"content": "", "items": []}}], "id": 2, "sub_definition": false}, {"type_": "definition", "elements": [{"type_": "explanation", "content": "det som produseres", "items": []}, {"type_": "explanation", "content": "framstilte varer (i et land, en næringsgren $ en virksomhet)", "items": [{"type_": "entity", "id": "el"}]}, {"type_": "example", "quote": {"content": "en samlet $ på 20 000 tonn", "items": [{"type_": "usage", "items": [], "text": "produksjon"}]}, "explanation": {"content": "", "items": []}}], "id": 5, "sub_definition": false}, {"type_": "definition", "elements": [{"type_": "explanation", "content": "resultat av skapende virksomhet", "items": []}, {"type_": "example", "quote": {"content": "Picassos samlede $", "items": [{"type_": "usage", "items": [], "text": "produksjon"}]}, "explanation": {"content": "", "items": []}}, {"type_": "example", "quote": {"content": "tv-serien ble kanalens dyreste produksjon", "items": []}, "explanation": {"content": "", "items": []}}], "id": 3, "sub_definition": false}], "id": 4, "sub_definition": false}]}, "to_index": ["produksjon", "produksjon", "produksjonen", "produksjon", "produksjon"], "author": "15", "edit_state": "Eksisterende", "referers": [{"article_id": 2541, "hgno": 0, "lemma": "arbeidskraft"}, {"article_id": 11525, "hgno": 0, "lemma": "døgnproduksjon"}, {"article_id": 13528, "hgno": 0, "lemma": "fabrikasjon"}, {"article_id": 13529, "hgno": 0, "lemma": "fabrikat"}, {"article_id": 112801, "hgno": 0, "lemma": "filmproduksjon"}, {"article_id": 117104, "hgno": 0, "lemma": "hormonproduksjon"}, {"article_id": 127730, "hgno": 0, "lemma": "kunstnerskap"}, {"article_id": 65966, "hgno": 0, "lemma": "utvikling"}, {"article_id": 17573, "hgno": 0, "lemma": "framstilling"}], "status": 8, "updated": "2024-04-11 13:58:04"}