{"article_id": 47298, "submitted": "2024-08-19 08:05:44", "suggest": ["ragg"], "lemmas": [{"final_lexeme": "ragg", "hgno": 0, "id": 54354, "inflection_class": "n1", "lemma": "ragg", "paradigm_info": [{"from": "1996-01-01", "inflection": [{"tags": ["Sing", "Ind"], "word_form": "ragg"}, {"tags": ["Sing", "Def"], "word_form": "ragget"}, {"tags": ["Plur", "Ind"], "word_form": "ragg"}, {"tags": ["Plur", "Def"], "word_form": "ragga"}], "inflection_group": "NOUN_regular", "paradigm_id": 669, "standardisation": "STANDARD", "tags": ["NOUN", "Neuter"], "to": null}, {"from": "1996-01-01", "inflection": [{"tags": ["Sing", "Ind"], "word_form": "ragg"}, {"tags": ["Sing", "Def"], "word_form": "ragget"}, {"tags": ["Plur", "Ind"], "word_form": "ragg"}, {"tags": ["Plur", "Def"], "word_form": "raggene"}], "inflection_group": "NOUN_regular", "paradigm_id": 679, "standardisation": "STANDARD", "tags": ["NOUN", "Neuter"], "to": null}], "split_inf": false}], "body": {"etymology": [{"type_": "etymology_reference", "content": "$ $", "items": [{"type_": "entity", "id": "norr."}, {"type_": "usage", "text": "rǫgg"}]}], "definitions": [{"type_": "definition", "elements": [{"type_": "explanation", "content": "lang, stri og bustete dyrepels", "items": [], "attest": []}, {"type_": "explanation", "content": "langt, stritt og bustete hår", "items": [], "attest": []}, {"type_": "example", "quote": {"content": "det er på tide å klippe ragget", "items": []}, "explanation": {"content": "", "items": []}, "attest": []}, {"type_": "compound_list", "elements": [{"type_": "article_ref", "article_id": 19367, "lemmas": [{"type_": "lemma", "hgno": 0, "id": 22641, "lemma": "geiteragg"}]}], "intro": {"content": "som etterledd i ord som", "items": []}}], "id": 2, "sub_definition": false}]}, "to_index": ["rǫgg"], "author": "27", "edit_state": "Eksisterende", "referers": [{"article_id": 47302, "hgno": 0, "lemma": "raggete"}], "status": 8, "updated": "2024-08-22 14:36:03"}